timeseriesql_appoptics/__init__.py
timeseriesql_appoptics-0.1.0.dist-info/METADATA
timeseriesql_appoptics-0.1.0.dist-info/WHEEL
timeseriesql_appoptics-0.1.0.dist-info/top_level.txt
timeseriesql_appoptics-0.1.0.dist-info/RECORD
